.travis.yml
README.rst
bootstrap.py
buildout.cfg
pre-commit-check.sh
setup.py
validation-files.yaml
validation-options.yaml
docs/HISTORY.rst
docs/LICENSE.rst
docs/api.rst
docs/conf.py
docs/conventions.rst
docs/env.rst
docs/index.rst
docs/release.rst
src/ucg/__init__.py
src/ucg/exceptions.py
src/ucg.egg-info/PKG-INFO
src/ucg.egg-info/SOURCES.txt
src/ucg.egg-info/dependency_links.txt
src/ucg.egg-info/not-zip-safe
src/ucg.egg-info/requires.txt
src/ucg.egg-info/top_level.txt
src/ucg/tests/__init__.py
src/ucg/tests/test_ucg.py