Metadata-Version: 1.1
Name: ucg
Version: 0.1.1
Summary: Python bindings for UCG API
Home-page: http://www.niteoweb.com
Author: NiteoWeb Ltd.
Author-email: info@niteoweb.com
License: BSD
Keywords: API spinner UCG
Platform: UNKNOWN
Classifier: Programming Language :: Python
Classifier: Topic :: Internet :: WWW/HTTP
